supersymmetry/__init__.py
supersymmetry/supersymmetry.py
supersymmetry-0.0.1.dist-info/METADATA
supersymmetry-0.0.1.dist-info/WHEEL
supersymmetry-0.0.1.dist-info/top_level.txt
supersymmetry-0.0.1.dist-info/RECORD
