Metadata-Version: 2.4
Name: Supersymmetry
Version: 0.0.1
Summary: Multimodal search, maximized for your potential
Requires-Python: >=3.10
